MANIFEST.in
README.md
setup.cfg
setup.py
assetman/__init__.py
assetman.egg-info/PKG-INFO
assetman.egg-info/SOURCES.txt
assetman.egg-info/dependency_links.txt
assetman.egg-info/not-zip-safe
assetman.egg-info/requires.txt
assetman.egg-info/top_level.txt
assetman/core/__init__.py
assetman/core/assets.py
assetman/service/__init__.py
assetman/service/s3.py
assetman/tests/__init__.py
assetman/tests/test_assetman.py
assetman/tests/test_core.py