Metadata-Version: 1.1
Name: assetman
Version: 0.0.2
Summary: Generic blob-data asset manager that provides an API, CLI interface, for managing S3 assets and the respective CloudFront delivery setup.
Home-page: http://github.com/petermelias/assetman
Author: Peter M. Elias
Author-email: petermelias@gmail.com
License: BSD
Platform: any
Classifier: Environment :: Web Environment
Classifier: Intended Audience :: Developers
Classifier: License :: OSI Approved :: BSD License
Classifier: Operating System :: OS Independent
Classifier: Programming Language :: Python
Classifier: Topic :: Internet :: WWW/HTTP :: Dynamic Content
Classifier: Topic :: Software Development :: Libraries :: Python Modules
